tests/__init__.py
tests/utils.py
tests/_test_local/__init__.py
tests/_test_local/_test_adjoint_performance.py
tests/_test_local/_test_data_performance.py
tests/_test_local/_test_fit_web.py
tests/_test_local/_test_plugins_web.py
tests/_test_local/_test_web.py
tests/test_components/__init__.py
tests/test_components/test_IO.py
tests/test_components/test_apodization.py
tests/test_components/test_base.py
tests/test_components/test_boundaries.py
tests/test_components/test_custom.py
tests/test_components/test_field_projection.py
tests/test_components/test_geometry.py
tests/test_components/test_grid.py
tests/test_components/test_grid_spec.py
tests/test_components/test_medium.py
tests/test_components/test_meshgenerate.py
tests/test_components/test_mode.py
tests/test_components/test_monitor.py
tests/test_components/test_sidewall.py
tests/test_components/test_simulation.py
tests/test_components/test_source.py
tests/test_components/test_types.py
tests/test_components/test_viz.py
tests/test_data/__init__.py
tests/test_data/test_data_arrays.py
tests/test_data/test_monitor_data.py
tests/test_data/test_sim_data.py
tests/test_package/__init__.py
tests/test_package/test_config.py
tests/test_package/test_log.py
tests/test_package/test_main.py
tests/test_package/test_make_script.py
tests/test_package/test_material_library.py
tests/test_package/test_parametric_variants.py
tests/test_plugins/__init__.py
tests/test_plugins/test_adjoint.py
tests/test_plugins/test_component_modeler.py
tests/test_plugins/test_dispersion_fitter.py
tests/test_plugins/test_mode_solver.py
tests/test_plugins/test_polyslab.py
tests/test_plugins/test_resonance_finder.py
tests/test_web/__init__.py
tests/test_web/mock_web.py
tests/test_web/test_auth.py
tests/test_web/test_cli.py
tests/test_web/test_material_fitter.py
tests/test_web/test_task.py
tests/test_web/test_tidy3d_folder.py
tests/test_web/test_tidy3d_material_library.py
tests/test_web/test_tidy3d_task.py
tests/test_web/test_webapi.py
tidy3d/__init__.py
tidy3d_beta-2.0.0.dist-info/LICENSE
tidy3d_beta-2.0.0.dist-info/METADATA
tidy3d_beta-2.0.0.dist-info/WHEEL
tidy3d_beta-2.0.0.dist-info/entry_points.txt
tidy3d_beta-2.0.0.dist-info/top_level.txt
tidy3d_beta-2.0.0.dist-info/RECORD
