Metadata-Version: 2.1
Name: tidy3d-beta
Version: 2.0.0
Summary: A fast FDTD solver
Home-page: https://github.com/flexcompute/tidy3d
Author: Tyler Hughes
Author-email: tyler@flexcompute.com
Project-URL: Bug Tracker, https://github.com/flexcompute/tidy3d/issues
Classifier: Programming Language :: Python :: 3
Classifier: License :: OSI Approved :: MIT License
Classifier: Operating System :: OS Independent
Requires-Python: >=3.7
License-File: LICENSE
Requires-Dist: scipy
Requires-Dist: pyroots (>=0.5.0)
Requires-Dist: xarray (>=0.16.2)
Requires-Dist: importlib-metadata (>=6.0.0)
Requires-Dist: h5netcdf (==1.0.2)
Requires-Dist: h5py (>=3.0.0)
Requires-Dist: rich (<12.6.0)
Requires-Dist: matplotlib
Requires-Dist: shapely (>=2.0)
Requires-Dist: pydantic (<2.0.0,>=1.10.0)
Requires-Dist: PyYAML
Requires-Dist: dask
Requires-Dist: toml
Requires-Dist: nest-asyncio
Requires-Dist: boto3 (==1.23.1)
Requires-Dist: requests
Requires-Dist: pyjwt
Requires-Dist: click (==8.0.3)
Requires-Dist: responses
Provides-Extra: dev
Requires-Dist: pre-commit ; extra == 'dev'
Requires-Dist: black (==22.3.0) ; extra == 'dev'
Requires-Dist: pylint ; extra == 'dev'
Requires-Dist: tox ; extra == 'dev'
Requires-Dist: pytest ; extra == 'dev'
Requires-Dist: pytest-timeout ; extra == 'dev'
Requires-Dist: memory-profiler ; extra == 'dev'
Requires-Dist: dill ; extra == 'dev'
Provides-Extra: gdspy
Requires-Dist: gdspy ; extra == 'gdspy'
Provides-Extra: gdstk
Requires-Dist: gdstk ; extra == 'gdstk'
Provides-Extra: jax
Requires-Dist: jaxlib (>=0.3.14) ; (platform_system != "Windows") and extra == 'jax'
Requires-Dist: jax[cpu] (>=0.3.14) ; (platform_system != "Windows") and extra == 'jax'
Requires-Dist: jaxlib (==0.3.14) ; (platform_system == "Windows") and extra == 'jax'
Requires-Dist: jax[cpu] (==0.3.14) ; (platform_system == "Windows") and extra == 'jax'
Provides-Extra: trimesh
Requires-Dist: trimesh (==3.20.0) ; extra == 'trimesh'
Requires-Dist: networkx (<=3.0,>=2.6.3) ; extra == 'trimesh'
Requires-Dist: rtree (==1.0.1) ; extra == 'trimesh'
